setup.py
week_time_ex_sar_forex_next3/__init__.py
week_time_ex_sar_forex_next3/week_time_ex_sar_forex_next3.py
week_time_ex_sar_forex_next3.egg-info/PKG-INFO
week_time_ex_sar_forex_next3.egg-info/SOURCES.txt
week_time_ex_sar_forex_next3.egg-info/dependency_links.txt
week_time_ex_sar_forex_next3.egg-info/not-zip-safe
week_time_ex_sar_forex_next3.egg-info/top_level.txt