Metadata-Version: 1.0
Name: week-time-ex-sar-forex-next3
Version: 1.1
Summary: week_time_ex_sar_forex_next3
Home-page: UNKNOWN
Author: omid
Author-email: UNKNOWN
License: UNKNOWN
Platform: UNKNOWN
